lambda_base/__init__.py
lambda_base/enhanced_request.py
lambda_base/http_methods.py
lambda_base/jsonapi.py
lambda_base/request_handler.py
lambda_base/response_handler.py
lambda_base/route.py
lambda_base/route_holder.py
lambda_base/route_parser.py
lambda_base/singleton.py
lambda_base/validations/__init__.py
py_lambda_base-0.0.6.post1.dist-info/LICENSE
py_lambda_base-0.0.6.post1.dist-info/METADATA
py_lambda_base-0.0.6.post1.dist-info/WHEEL
py_lambda_base-0.0.6.post1.dist-info/top_level.txt
py_lambda_base-0.0.6.post1.dist-info/RECORD
